prestige_irc/__init__.py
prestige_irc/commands.py
prestige_irc/connection.py
prestige_irc/irc_connection.py
prestige_irc/message.py
prestige_irc-0.0.6.dist-info/LICENSE
prestige_irc-0.0.6.dist-info/METADATA
prestige_irc-0.0.6.dist-info/WHEEL
prestige_irc-0.0.6.dist-info/top_level.txt
prestige_irc-0.0.6.dist-info/RECORD
