Metadata-Version: 2.1
Name: prestige-irc
Version: 0.0.6
Summary: A simple API for IRC networks
Home-page: https://github.com/avahe-kellenberger/prestige_irc
Author: Avahe Kellenberger
Author-email: avahe@protonmail.ch
License: UNKNOWN
Platform: UNKNOWN
Classifier: Programming Language :: Python :: 3
Classifier: License :: OSI Approved :: GNU General Public License v2 (GPLv2)
Classifier: Operating System :: OS Independent
